errs/__init__.py
errs/errs.py
errs-0.1.1.dist-info/AUTHORS.rst
errs-0.1.1.dist-info/LICENSE
errs-0.1.1.dist-info/METADATA
errs-0.1.1.dist-info/WHEEL
errs-0.1.1.dist-info/top_level.txt
errs-0.1.1.dist-info/RECORD
