Metadata-Version: 2.1
Name: errs
Version: 0.1.1
Summary: Type-safe error handling for Python.
Home-page: https://github.com/nicksettje/errs
Author: Nick Frederick Settje
Author-email: nsettje@alumni.stanford.edu
License: MIT license
Keywords: errs
Platform: UNKNOWN
Classifier: Development Status :: 2 - Pre-Alpha
Classifier: Intended Audience :: Developers
Classifier: License :: OSI Approved :: MIT License
Classifier: Natural Language :: English
Classifier: Programming Language :: Python :: 2
Classifier: Programming Language :: Python :: 2.7
Classifier: Programming Language :: Python :: 3
Classifier: Programming Language :: Python :: 3.4
Classifier: Programming Language :: Python :: 3.5
Classifier: Programming Language :: Python :: 3.6
Classifier: Programming Language :: Python :: 3.7
